ansible_collections/__init__.py
ansible_collections/ansible/__init__.py
ansible_collections/ansible/mockable/__init__.py
ansible_collections/ansible/mockable/plugins/__init__.py
ansible_collections/ansible/mockable/plugins/callback/__init__.py
ansible_collections/ansible/mockable/plugins/callback/mockable.py
ansible_collections/ansible/mockable/plugins/module_utils/__init__.py
ansible_collections/ansible/mockable/plugins/module_utils/mockable.py
ansible_mockable-1.0.0.dist-info/LICENSE
ansible_mockable-1.0.0.dist-info/METADATA
ansible_mockable-1.0.0.dist-info/WHEEL
ansible_mockable-1.0.0.dist-info/top_level.txt
ansible_mockable-1.0.0.dist-info/RECORD
